pull_request_auto_labeler.py
pull_request_auto_labeler-0.12.dist-info/LICENSE
pull_request_auto_labeler-0.12.dist-info/METADATA
pull_request_auto_labeler-0.12.dist-info/WHEEL
pull_request_auto_labeler-0.12.dist-info/entry_points.txt
pull_request_auto_labeler-0.12.dist-info/top_level.txt
pull_request_auto_labeler-0.12.dist-info/RECORD
