Metadata-Version: 2.1
Name: pull-request-auto-labeler
Version: 0.12
Summary: Automatically label Github pull requests based on elements of the PR title. Expects Jira style ticket code(PROJ-100) in PR title
Home-page: https://github.com/markddavidoff/pull_request_auto_labeler
Author: Mark Davidoff
Author-email: markddavidoff@gmail.com
License: MIT
Platform: UNKNOWN
Requires-Dist: github3.py (==1.2.0)
Requires-Dist: tqdm (==4.33.0)
